obfuskey/__init__.py
obfuskey/_constants.py
obfuskey/_math.py
obfuskey/_obfusbit.py
obfuskey/_obfusbit_schema.py
obfuskey/_obfuskey.py
obfuskey/_types.py
obfuskey/alphabets.py
obfuskey/exceptions.py
obfuskey/utils.py
obfuskey-0.2.0.dist-info/LICENSE
obfuskey-0.2.0.dist-info/METADATA
obfuskey-0.2.0.dist-info/WHEEL
obfuskey-0.2.0.dist-info/RECORD
