Metadata-Version: 2.1
Name: obfuskey
Version: 0.2.0
Summary: A small library for obfuscating integer values to key strings using a set length and alphabet.
Home-page: https://github.com/bnlucas/obfuskey
License: MIT
Keywords: obfuskey,obfuscate,basehash,key
Author: Nathan Lucas
Author-email: nathan@bnlucas.com
Requires-Python: >=3.9,<3.13
Classifier: Intended Audience :: Developers
Classifier: License :: OSI Approved :: MIT License
Classifier: Natural Language :: English
Classifier: Operating System :: OS Independent
Classifier: Programming Language :: Python :: 3
Classifier: Programming Language :: Python :: 3.9
Classifier: Programming Language :: Python :: 3.10
Classifier: Programming Language :: Python :: 3.11
Classifier: Programming Language :: Python :: 3.12
Classifier: Programming Language :: Python :: 3.8
Classifier: Topic :: Software Development :: Libraries :: Python Modules
Classifier: Topic :: Utilities
Provides-Extra: gmpy2
Project-URL: Repository, https://github.com/bnlucas/obfuskey
